mutapath/__init__.py
mutapath/decorator.py
mutapath/defaults.py
mutapath/exceptions.py
mutapath/immutapath.py
mutapath/lock_dummy.py
mutapath/mutapath.py
mutapath-0.17.1.dist-info/LICENSE
mutapath-0.17.1.dist-info/METADATA
mutapath-0.17.1.dist-info/WHEEL
mutapath-0.17.1.dist-info/RECORD
