Metadata-Version: 2.1
Name: mutapath
Version: 0.17.1
Summary: mutable pathlib
Home-page: https://mutapath.fax.fyi
License: LGPL-3.0
Keywords: pathlib,mutable,path
Author: matfax
Author-email: mat@fax.fyi
Requires-Python: >=3.8,<4.0
Classifier: License :: OSI Approved :: GNU Lesser General Public License v3 (LGPLv3)
Classifier: Programming Language :: Python :: 3
Classifier: Programming Language :: Python :: 3.8
Classifier: Programming Language :: Python :: 3.9
Classifier: Programming Language :: Python :: 3.10
Classifier: Programming Language :: Python :: 3.11
Provides-Extra: mashumaro
Requires-Dist: cached-property (>=1.5.2,<1.6.0)
Requires-Dist: filelock (>=3.12.2,<3.13.0)
Requires-Dist: mashumaro (>=3,<=3.8.1) ; extra == "mashumaro"
Requires-Dist: path (>=16.2,<=16.7.1)
Requires-Dist: singletons (>=0.2.5,<0.3.0)
Project-URL: Documentation, https://mutapath.fax.fyi
Project-URL: Repository, https://github.com/matfax/mutapath
